{
  "type": "membership_application",
  "membershipId": "FLO2Hvm5",
  "fullName": "Dr Piyush Bhardwaj",
  "email": "c2piyushsharma@gmail.com",
  "phone": "9024922510",
  "linkedin": "",
  "profession": "Student",
  "country": "India",
  "otherCountry": "",
  "region": "",
  "cityState": "College, Jaipur .",
  "status": "accepted",
  "verified": true,
  "submittedAt": "2026-04-27T05:58:11.166Z",
  "timestamp": "2026-04-27T05:58:11.166Z",
  "whatsapp": "9024922510",
  "name": "Dr Piyush Bhardwaj",
  "location": "",
  "qualification": "Bachelor",
  "membership_type": "Professional Member",
  "areas_of_interest": [
    "Myopia Control",
    "Contact Lens",
    "Pediatric Optometry",
    "Sports Vision",
    "Vision Therapy"
  ],
  "dob": "12/01/1995",
  "gender": "Male",
  "institution": "College, Jaipur ."
}