{
  "name": "Gitika kumari",
  "email": "gitikakumari35@gmail.com",
  "phone": "637560867863756",
  "whatsapp": "6375608678",
  "dob": "14/10/2002",
  "gender": "Female",
  "country": "India",
  "institution": "university",
  "qualification": "Degree",
  "profession": "Optometrist",
  "membership_type": "Student Member",
  "membership_id": "FL-OPT-7927",
  "areas_of_interest": [
    "Myopia Control",
    "Contact Lens",
    "Pediatric Optometry",
    "Sports Vision",
    "Vision Therapy"
  ],
  "registered_at": "20/07/2025 18:22:38",
  "source": "optobharat_old_members"
}